RooR/__init__.py
RooR/attack_simulation.py
RooR/behavioral_analysis.py
RooR/report_generation.py
roor-0.0.4.dist-info/METADATA
roor-0.0.4.dist-info/WHEEL
roor-0.0.4.dist-info/top_level.txt
roor-0.0.4.dist-info/RECORD
