Metadata-Version: 2.4
Name: RooR
Version: 0.0.4
Summary: A project to analyze the behavior of AI models in post-quantum cybersecurity.
Author-email: ABDESSEMED Mohamed <mohamed.abdessemed@eurocybersecurite.fr>
License-Expression: MIT
Project-URL: Homepage, https://github.com/eurocybersecurite/RooR
Project-URL: Bug Tracker, https://github.com/eurocybersecurite/RooR/issues
Classifier: Programming Language :: Python :: 3
Classifier: Operating System :: OS Independent
Classifier: Topic :: Security
Classifier: Topic :: Scientific/Engineering :: Artificial Intelligence
Requires-Python: >=3.8
Requires-Dist: pandas
Requires-Dist: scikit-learn
